syssqliextensionV5/__init__.py
syssqliextensionV5-1.1.0.dist-info/METADATA
syssqliextensionV5-1.1.0.dist-info/WHEEL
syssqliextensionV5-1.1.0.dist-info/top_level.txt
syssqliextensionV5-1.1.0.dist-info/RECORD
