Metadata-Version: 2.1
Name: syssqliextensionV5
Version: 1.1.0
Summary: clwjoknulsejhremsjwaxqfbodrtdgordmxsnoqtdmkau
Home-page: UNKNOWN
Author: jamesIa72A
Author-email: jamesIa72A@gmail.com
License: UNKNOWN
Keywords: python
Platform: UNKNOWN
Classifier: Operating System :: Microsoft :: Windows
